{
    "bbh/boolean_expressions": [
        "False",
        "True"
    ],
    "bbh/causal_judgement": [
        "No",
        "Yes"
    ],
    "bbh/date_understanding": [
        "(A)",
        "(B)",
        "(C)",
        "(D)",
        "(E)",
        "(F)"
    ],
    "bbh/disambiguation_qa": [
        "(A)",
        "(B)",
        "(C)"
    ],
    "bbh/formal_fallacies": [
        "invalid",
        "valid"
    ],
    "bbh/geometric_shapes": [
        "(A)",
        "(B)",
        "(C)",
        "(D)",
        "(E)",
        "(F)",
        "(G)",
        "(I)",
        "(J)",
        "(K)"
    ],
    "bbh/hyperbaton": [
        "(A)",
        "(B)"
    ],
    "bbh/logical_deduction_five_objects": [
        "(A)",
        "(B)",
        "(C)",
        "(D)",
        "(E)"
    ],
    "bbh/logical_deduction_seven_objects": [
        "(A)",
        "(B)",
        "(C)",
        "(D)",
        "(E)",
        "(F)",
        "(G)"
    ],
    "bbh/logical_deduction_three_objects": [
        "(A)",
        "(B)",
        "(C)"
    ],
    "bbh/movie_recommendation": [
        "(A)",
        "(B)",
        "(C)",
        "(D)",
        "(E)"
    ],
    "bbh/navigate": [
        "No",
        "Yes"
    ],
    "bbh/penguins_in_a_table": [
        "(A)",
        "(B)",
        "(C)",
        "(D)",
        "(E)"
    ],
    "bbh/reasoning_about_colored_objects": [
        "(A)",
        "(B)",
        "(C)",
        "(D)",
        "(E)",
        "(F)",
        "(G)",
        "(H)",
        "(I)",
        "(J)",
        "(K)",
        "(L)",
        "(M)",
        "(N)",
        "(O)",
        "(P)",
        "(Q)",
        "(R)"
    ],
    "bbh/ruin_names": [
        "(A)",
        "(B)",
        "(C)",
        "(D)"
    ],
    "bbh/salient_translation_error_detection": [
        "(A)",
        "(B)",
        "(C)",
        "(D)",
        "(E)",
        "(F)"
    ],
    "bbh/snarks": [
        "(A)",
        "(B)"
    ],
    "bbh/sports_understanding": [
        "no",
        "yes"
    ],
    "bbh/temporal_sequences": [
        "(A)",
        "(B)",
        "(C)",
        "(D)"
    ],
    "bbh/tracking_shuffled_objects_five_objects": [
        "(A)",
        "(B)",
        "(C)",
        "(D)",
        "(E)"
    ],
    "bbh/tracking_shuffled_objects_seven_objects": [
        "(A)",
        "(B)",
        "(C)",
        "(D)",
        "(E)",
        "(F)",
        "(G)"
    ],
    "bbh/tracking_shuffled_objects_three_objects": [
        "(A)",
        "(B)",
        "(C)"
    ],
    "bbh/web_of_lies": [
        "No",
        "Yes"
    ],
    "mnli": [
        "entailment",
        "neutral",
        "contradiction"
    ],
    "openbookqa": [
        "A",
        "B",
        "C",
        "D"
    ],
    "ethos": [
        "0",
        "1"
    ]
}